ecoindex/cli/VERSION
ecoindex/cli/__init__.py
ecoindex/cli/app.py
ecoindex/cli/arguments_handler.py
ecoindex/cli/console_output.py
ecoindex/cli/crawl.py
ecoindex/cli/helper.py
ecoindex/cli/report.py
ecoindex/cli/sitemap.py
ecoindex/cli/template.html
ecoindex/compute/VERSION
ecoindex/compute/__init__.py
ecoindex/compute/ecoindex.py
ecoindex/config/__init__.py
ecoindex/config/settings.py
ecoindex/data/__init__.py
ecoindex/data/colors.py
ecoindex/data/grades.py
ecoindex/data/medians.py
ecoindex/data/quantiles.py
ecoindex/data/targets.py
ecoindex/exceptions/__init__.py
ecoindex/exceptions/scraper.py
ecoindex/exceptions/worker.py
ecoindex/models/__init__.py
ecoindex/models/api.py
ecoindex/models/cli.py
ecoindex/models/compute.py
ecoindex/models/enums.py
ecoindex/models/response_examples.py
ecoindex/models/scraper.py
ecoindex/models/sort.py
ecoindex/models/tasks.py
ecoindex/scraper/VERSION
ecoindex/scraper/__init__.py
ecoindex/scraper/helper.py
ecoindex/scraper/scrap.py
ecoindex/utils/__init__.py
ecoindex/utils/cli_translations/en.yml
ecoindex/utils/cli_translations/fr.yml
ecoindex/utils/files.py
ecoindex/utils/screenshots.py
ecoindex_cli-2.30.0.dist-info/METADATA
ecoindex_cli-2.30.0.dist-info/WHEEL
ecoindex_cli-2.30.0.dist-info/entry_points.txt
ecoindex_cli-2.30.0.dist-info/RECORD
